eek_add_mcp/__init__.py
eek_add_mcp-0.1.0.dist-info/WHEEL
eek_add_mcp-0.1.0.dist-info/entry_points.txt
eek_add_mcp-0.1.0.dist-info/METADATA
eek_add_mcp-0.1.0.dist-info/RECORD
