Metadata-Version: 2.3
Name: eek-add-mcp
Version: 0.1.0
Summary: Add your description here
Author: eeknight666
Author-email: eeknight666 <eeknight666@gmail.com>
Requires-Dist: mcp[cli]>=1.12.3
Requires-Python: >=3.12
